{"x":0,"type":"View","selectedBox":59,"selecteID":59,"searchKey":"View","props":{"width":1334,"top":0,"right":0,"left":0,"height":750,"bottom":0},"nodeParent":-1,"maxID":90,"loadList3D":[],"loadList":["stopImg/guanka_bg.png","stopImg/top_di.png","stopImg/topbtn_di1.png","stopImg/fanhui.png","stopImg/icon_jinbi.png","stopImg/icon_+.png","stopImg/set_bar_on.png","stopImg/set_bar_slider.png","stopImg/hand_left.png","stopImg/set_dui_di.png","stopImg/duigou_kuai-2.png","stopImg/gear_img.png","stopImg/set_off.png","stopImg/img_set_anjian.png","stopImg/img_setfangxangpan.png"],"label":"View","isOpen":true,"isDirectory":true,"isAniNode":true,"hasChild":true,"compId":2,"child":[{"x":15,"type":"Image","searchKey":"Image,bg","props":{"top":0,"skin":"stopImg/guanka_bg.png","right":0,"name":"bg","left":0,"bottom":0},"nodeParent":2,"label":"bg","isDirectory":false,"isAniNode":true,"hasChild":false,"compId":4,"child":[]},{"x":15,"type":"Box","searchKey":"Box","props":{"y":0,"x":0,"right":0,"left":0},"nodeParent":2,"label":"Box","isOpen":true,"isDirectory":true,"isAniNode":true,"hasChild":true,"compId":54,"child":[{"x":30,"type":"Image","searchKey":"Image","props":{"top":0,"skin":"stopImg/top_di.png","right":0,"left":0,"height":71},"nodeParent":54,"label":"Image","isDirectory":false,"isAniNode":true,"hasChild":false,"compId":55,"child":[]},{"x":30,"type":"Image","searchKey":"Image,closeBtn","props":{"var":"closeBtn","top":0,"skin":"stopImg/topbtn_di1.png","left":0},"nodeParent":54,"label":"closeBtn","isOpen":null,"isDirectory":true,"isAniNode":true,"hasChild":true,"compId":56,"child":[{"type":"Image","searchKey":"Image","props":{"skin":"stopImg/fanhui.png","left":29,"centerY":0},"nodeParent":56,"label":"Image","isDirectory":false,"isAniNode":true,"hasChild":false,"compId":57,"child":[]}]},{"x":30,"type":"Label","searchKey":"Label","props":{"top":20,"text":"Set","left":174,"fontSize":32,"font":"Arial","color":"#ffffff","bold":true},"nodeParent":54,"label":"Label","isDirectory":false,"isAniNode":true,"hasChild":false,"compId":58,"child":[]},{"x":30,"type":"Image","searchKey":"Image","props":{"visible":true,"top":-113,"skin":"stopImg/icon_jinbi.png","left":779},"nodeParent":54,"label":"Image","isOpen":null,"isDirectory":true,"isAniNode":true,"hasChild":true,"compId":59,"child":[{"type":"Label","searchKey":"Label,goldNum","props":{"var":"goldNum","text":"5688","fontSize":25,"color":"#ffffff","centerY":0,"centerX":71},"nodeParent":59,"label":"goldNum","isDirectory":false,"isAniNode":true,"hasChild":false,"compId":60,"child":[]},{"type":"Box","searchKey":"Box,addGold","props":{"y":0,"x":0,"width":50,"var":"addGold","left":133,"height":50,"centerY":0},"nodeParent":59,"label":"addGold","isDirectory":true,"isAniNode":true,"hasChild":true,"compId":88,"child":[{"type":"Image","searchKey":"Image","props":{"y":11,"skin":"stopImg/icon_+.png","centerY":0,"centerX":0},"nodeParent":88,"label":"Image","isDirectory":false,"isAniNode":true,"hasChild":false,"compId":89,"child":[]}]}]}]},{"x":15,"type":"Label","searchKey":"Label","props":{"top":156,"text":"Music","left":277,"fontSize":32,"font":"Arial","color":"#ffffff","bold":true},"nodeParent":2,"label":"Label","isOpen":null,"isDirectory":true,"isAniNode":true,"hasChild":true,"compId":41,"child":[{"type":"Image","searchKey":"Image,musicBg","props":{"var":"musicBg","top":48,"skin":"stopImg/set_bar_on.png"},"nodeParent":41,"label":"musicBg","isDirectory":true,"isAniNode":true,"hasChild":true,"compId":63,"child":[{"type":"Image","searchKey":"Image,musicTig","props":{"x":305,"var":"musicTig","skin":"stopImg/set_bar_slider.png","centerY":0},"nodeParent":63,"label":"musicTig","isDirectory":false,"isAniNode":true,"hasChild":false,"compId":64,"child":[]}]}]},{"x":15,"type":"Label","searchKey":"Label","props":{"y":156,"top":156,"text":"Audio","left":770,"fontSize":32,"font":"Arial","color":"#ffffff","bold":true},"nodeParent":2,"label":"Label","isOpen":null,"isDirectory":true,"isAniNode":true,"hasChild":true,"compId":65,"child":[{"type":"Image","searchKey":"Image,audioBg","props":{"var":"audioBg","top":48,"skin":"stopImg/set_bar_on.png"},"nodeParent":65,"label":"audioBg","isDirectory":true,"isAniNode":true,"hasChild":true,"compId":66,"child":[{"type":"Image","searchKey":"Image,audioTig","props":{"x":305,"var":"audioTig","skin":"stopImg/set_bar_slider.png","centerY":0},"nodeParent":66,"label":"audioTig","isDirectory":false,"isAniNode":true,"hasChild":false,"compId":67,"child":[]}]}]},{"x":15,"type":"Label","searchKey":"Label","props":{"top":280,"text":"How to operate","fontSize":32,"font":"Arial","color":"#ffffff","centerX":0},"nodeParent":2,"label":"Label","isDirectory":false,"isAniNode":true,"hasChild":false,"compId":69,"child":[]},{"x":15,"type":"Image","searchKey":"Image","props":{"top":348,"skin":"stopImg/hand_left.png","centerX":-245},"nodeParent":2,"label":"Image","isOpen":true,"isDirectory":true,"isAniNode":true,"hasChild":true,"compId":70,"child":[{"x":30,"type":"Label","searchKey":"Label","props":{"text":"Left-handed","left":-53,"fontSize":26,"font":"Arial","color":"#ffffff","centerY":45},"nodeParent":70,"label":"Label","isDirectory":false,"isAniNode":true,"hasChild":false,"compId":71,"child":[]},{"x":30,"type":"Image","searchKey":"Image,leftBtn","props":{"var":"leftBtn","skin":"stopImg/set_dui_di.png","left":86,"centerY":0},"nodeParent":70,"label":"leftBtn","isOpen":null,"isDirectory":true,"isAniNode":true,"hasChild":true,"compId":72,"child":[{"type":"Image","searchKey":"Image","props":{"width":27,"skin":"stopImg/duigou_kuai-2.png","mouseEnabled":false,"height":21,"centerY":0,"centerX":0},"nodeParent":72,"label":"Image","isDirectory":false,"isAniNode":true,"hasChild":false,"compId":73,"child":[]}]}]},{"x":15,"type":"Image","searchKey":"Image","props":{"top":348,"skin":"stopImg/hand_left.png","centerX":-16},"nodeParent":2,"label":"Image","isOpen":true,"isDirectory":true,"isAniNode":true,"hasChild":true,"compId":74,"child":[{"x":30,"type":"Label","searchKey":"Label","props":{"text":"Left-handed","left":-53,"fontSize":26,"font":"Arial","color":"#ffffff","centerY":44},"nodeParent":74,"label":"Label","isDirectory":false,"isAniNode":true,"hasChild":false,"compId":75,"child":[]},{"x":30,"type":"Image","searchKey":"Image,rightBtn","props":{"var":"rightBtn","skin":"stopImg/set_dui_di.png","left":85,"centerY":0},"nodeParent":74,"label":"rightBtn","isOpen":null,"isDirectory":true,"isAniNode":true,"hasChild":true,"compId":76,"child":[{"type":"Image","searchKey":"Image","props":{"skin":"stopImg/duigou_kuai-2.png","mouseEnabled":false,"centerY":0,"centerX":0},"nodeParent":76,"label":"Image","isDirectory":false,"isAniNode":true,"hasChild":false,"compId":77,"child":[]}]}]},{"x":15,"type":"Image","searchKey":"Image","props":{"top":348,"skin":"stopImg/gear_img.png","centerX":209},"nodeParent":2,"label":"Image","isOpen":true,"isDirectory":true,"isAniNode":true,"hasChild":true,"compId":84,"child":[{"x":30,"type":"Label","searchKey":"Label","props":{"text":"gear level ","left":-44,"fontSize":26,"font":"Arial","color":"#ffffff","centerY":46},"nodeParent":84,"label":"Label","isDirectory":false,"isAniNode":true,"hasChild":false,"compId":85,"child":[]},{"x":30,"type":"Image","searchKey":"Image,gearBtn","props":{"var":"gearBtn","skin":"stopImg/set_dui_di.png","left":76,"centerY":0},"nodeParent":84,"label":"gearBtn","isOpen":null,"isDirectory":true,"isAniNode":true,"hasChild":true,"compId":86,"child":[{"type":"Image","searchKey":"Image","props":{"skin":"stopImg/duigou_kuai-2.png","mouseEnabled":false,"centerY":0,"centerX":0},"nodeParent":86,"label":"Image","isDirectory":false,"isAniNode":true,"hasChild":false,"compId":87,"child":[]}]}]},{"x":15,"type":"Image","searchKey":"Image,keyBtn","props":{"var":"keyBtn","skin":"stopImg/set_off.png","centerX":-160,"bottom":102},"nodeParent":2,"label":"keyBtn","isOpen":true,"isDirectory":true,"isAniNode":true,"hasChild":true,"compId":78,"child":[{"x":30,"type":"Label","searchKey":"Label","props":{"top":13,"text":"Pushbutton","fontSize":26,"font":"Arial","color":"#ffffff","centerX":0,"bold":true},"nodeParent":78,"label":"Label","isDirectory":false,"isAniNode":true,"hasChild":false,"compId":80,"child":[]},{"x":30,"type":"Image","searchKey":"Image","props":{"skin":"stopImg/img_set_anjian.png","centerX":0,"bottom":55},"nodeParent":78,"label":"Image","isDirectory":false,"isAniNode":true,"hasChild":false,"compId":79,"child":[]}]},{"x":15,"type":"Image","searchKey":"Image,controlBtn","props":{"y":0,"var":"controlBtn","skin":"stopImg/set_off.png","centerX":160,"bottom":102},"nodeParent":2,"label":"controlBtn","isOpen":true,"isDirectory":true,"isAniNode":true,"hasChild":true,"compId":81,"child":[{"x":30,"type":"Label","searchKey":"Label","props":{"top":13,"text":"Steering Wheel","fontSize":20,"font":"Arial","color":"#ffffff","centerX":0,"bold":true},"nodeParent":81,"label":"Label","isDirectory":false,"isAniNode":true,"hasChild":false,"compId":82,"child":[]},{"x":30,"type":"Image","searchKey":"Image","props":{"skin":"stopImg/img_setfangxangpan.png","centerX":0,"bottom":55},"nodeParent":81,"label":"Image","isDirectory":false,"isAniNode":true,"hasChild":false,"compId":83,"child":[]}]}],"animations":[{"nodes":[],"name":"ani1","id":1,"frameRate":24,"action":0}]}